{
  "@context": "https://standard.site/",
  "@id": "https://octothorp.es/publishers/leaflet",
  "@type": "resolver",
  "meta": {
    "name": "Leaflet",
    "description": "Publishes to site.standard.document with pub.leaflet.content blocks",
    "lexicon": "site.standard.document"
  },
  "schema": {
    "site": { "from": ["documentRecord.site", "@id"], "required": true },
    "path": { "from": "documentRecord.path" },
    "title": { "from": ["title", "@id"], "required": true },
    "description": { "from": "description" },
    "textContent": { "from": "documentRecord.textContent" },
    "tags": { "from": "octothorpes", "postProcess": { "method": "extractTags" } },
    "publishedAt": { "from": "date", "postProcess": [{ "method": "date", "params": "iso8601" }, { "method": "default", "params": "now" }] }
  }
}
